MANIFEST.in
README.md
__init__.py
cookies.py
request.py
response.py
server.py
setup.py
maya_framework.egg-info/PKG-INFO
maya_framework.egg-info/SOURCES.txt
maya_framework.egg-info/dependency_links.txt
maya_framework.egg-info/requires.txt
maya_framework.egg-info/top_level.txt