Metadata-Version: 2.1
Name: maya-framework
Version: 0.0.1
Summary: Mini web-frame work package that provides basic web-programming features.
Home-page: https://github.com/Vladislavus1/Maya
Author: Vladislavus1
Author-email: vlydgames@gmail.com
Requires-Dist: jinja2==3.1.3
Requires-Dist: colorama==0.4.6
